netharn/__init__.py
netharn/analytic_for.py
netharn/api.py
netharn/device.py
netharn/exceptions.py
netharn/fit_harn.py
netharn/hyperparams.py
netharn/mixins.py
netharn/monitor.py
netharn/monkey.py
netharn/output_shape_for.py
netharn/receptive_field_for.py
netharn/analytic/__init__.py
netharn/analytic/analytic_for.py
netharn/analytic/output_shape_for.py
netharn/analytic/receptive_field_for.py
netharn/backbones/__init__.py
netharn/cli/__init__.py
netharn/cli/list_deployed.py
netharn/cli/manage_runs.py
netharn/criterions/__init__.py
netharn/criterions/contrastive_loss.py
netharn/criterions/focal.py
netharn/criterions/triplet.py
netharn/data/__init__.py
netharn/data/base.py
netharn/data/batch_samplers.py
netharn/data/channel_spec.py
netharn/data/coco_api.py
netharn/data/coerce_data.py
netharn/data/collate.py
netharn/data/data_containers.py
netharn/data/grab_camvid.py
netharn/data/grab_voc.py
netharn/data/mnist.py
netharn/data/toydata.py
netharn/data/voc.py
netharn/data/transforms/__init__.py
netharn/data/transforms/augmenter_base.py
netharn/data/transforms/augmenters.py
netharn/examples/__init__.py
netharn/examples/__main__.py
netharn/examples/cifar.py
netharn/examples/classification.py
netharn/examples/mnist.py
netharn/examples/object_detection.py
netharn/examples/segmentation.py
netharn/examples/sseg_camvid.py
netharn/examples/style_transfer.py
netharn/examples/style_transfer_orig.py
netharn/examples/yolo_voc.py
netharn/export/__init__.py
netharn/export/closer.py
netharn/export/deployer.py
netharn/export/exporter.py
netharn/initializers/__init__.py
netharn/initializers/core.py
netharn/initializers/functional.py
netharn/initializers/lsuv.py
netharn/initializers/pretrained.py
netharn/layers/__init__.py
netharn/layers/attention.py
netharn/layers/common.py
netharn/layers/conv_norm.py
netharn/layers/gauss.py
netharn/layers/mish.py
netharn/layers/norm.py
netharn/layers/perceptron.py
netharn/layers/rectify.py
netharn/layers/reshape.py
netharn/layers/swish.py
netharn-0.6.2.dist-info/LICENSE
netharn-0.6.2.dist-info/METADATA
netharn-0.6.2.dist-info/WHEEL
netharn-0.6.2.dist-info/top_level.txt
netharn-0.6.2.dist-info/RECORD
